<?xml version="1.0" encoding="UTF-8"?>
<configuration>
    <!-- Import Spring Boot defaults -->
    <include resource="org/springframework/boot/logging/logback/defaults.xml"/>

    <!-- Properties -->
    <property name="LOG_FILE" value="${LOG_FILE:-${LOG_PATH:-${LOG_TEMP:-${java.io.tmpdir:-/tmp}}}/spring.log}"/>
    <property name="APP_NAME" value="${spring.application.name:-crud-test-app}"/>
    <property name="ENVIRONMENT" value="${spring.profiles.active:-dev}"/>

    <!-- Console Appender with Pattern (Development) -->
    <appender name="CONSOLE" class="ch.qos.logback.core.ConsoleAppender">
        <filter class="ch.qos.logback.classic.filter.ThresholdFilter">
            <level>INFO</level>
        </filter>
        <encoder>
            <pattern>%d{yyyy-MM-dd HH:mm:ss.SSS} [%thread] %highlight(%-5level) %cyan(%logger{36}) - %msg%n</pattern>
            <charset>UTF-8</charset>
        </encoder>
    </appender>

    <!-- JSON Console Appender (Production) -->
    <appender name="JSON_CONSOLE" class="ch.qos.logback.core.ConsoleAppender">
        <encoder class="net.logstash.logback.encoder.LogstashEncoder">
            <!-- Add custom fields -->
            <customFields>{"app_name":"${APP_NAME}","environment":"${ENVIRONMENT}"}</customFields>

            <!-- Include caller data (file, line, method) -->
            <includeCallerData>false</includeCallerData>

            <!-- Include context (MDC) -->
            <includeContext>true</includeContext>

            <!-- Include structured arguments -->
            <includeStructuredArguments>true</includeStructuredArguments>

            <!-- Include non-structured arguments -->
            <includeNonStructuredArguments>false</includeNonStructuredArguments>

            <!-- Timestamp format -->
            <timestampPattern>yyyy-MM-dd'T'HH:mm:ss.SSSZZ</timestampPattern>

            <!-- Field names customization -->
            <fieldNames>
                <timestamp>@timestamp</timestamp>
                <version>@version</version>
                <message>message</message>
                <logger>logger_name</logger>
                <thread>thread_name</thread>
                <level>level</level>
                <levelValue>level_value</levelValue>
            </fieldNames>
        </encoder>
    </appender>

    <!-- File Appender with JSON (All Logs) -->
    <appender name="JSON_FILE" class="ch.qos.logback.core.rolling.RollingFileAppender">
        <file>${LOG_FILE}</file>
        <encoder class="net.logstash.logback.encoder.LogstashEncoder">
            <customFields>{"app_name":"${APP_NAME}","environment":"${ENVIRONMENT}"}</customFields>
            <includeContext>true</includeContext>
            <includeStructuredArguments>true</includeStructuredArguments>
            <timestampPattern>yyyy-MM-dd'T'HH:mm:ss.SSSZZ</timestampPattern>
        </encoder>
        <rollingPolicy class="ch.qos.logback.core.rolling.SizeAndTimeBasedRollingPolicy">
            <fileNamePattern>${LOG_FILE}.%d{yyyy-MM-dd}.%i.gz</fileNamePattern>
            <maxFileSize>100MB</maxFileSize>
            <maxHistory>30</maxHistory>
            <totalSizeCap>10GB</totalSizeCap>
        </rollingPolicy>
    </appender>

    <!-- Error File Appender with JSON (Errors Only) -->
    <appender name="ERROR_FILE" class="ch.qos.logback.core.rolling.RollingFileAppender">
        <file>${LOG_PATH:-${LOG_TEMP:-${java.io.tmpdir:-/tmp}}}/error.log</file>
        <filter class="ch.qos.logback.classic.filter.LevelFilter">
            <level>ERROR</level>
            <onMatch>ACCEPT</onMatch>
            <onMismatch>DENY</onMismatch>
        </filter>
        <encoder class="net.logstash.logback.encoder.LogstashEncoder">
            <customFields>{"app_name":"${APP_NAME}","environment":"${ENVIRONMENT}","log_type":"error"}</customFields>
            <includeContext>true</includeContext>
            <includeStructuredArguments>true</includeStructuredArguments>
            <includeCallerData>true</includeCallerData>
            <timestampPattern>yyyy-MM-dd'T'HH:mm:ss.SSSZZ</timestampPattern>
        </encoder>
        <rollingPolicy class="ch.qos.logback.core.rolling.SizeAndTimeBasedRollingPolicy">
            <fileNamePattern>${LOG_PATH:-${LOG_TEMP:-${java.io.tmpdir:-/tmp}}}/error.%d{yyyy-MM-dd}.%i.gz</fileNamePattern>
            <maxFileSize>50MB</maxFileSize>
            <maxHistory>90</maxHistory>
            <totalSizeCap>5GB</totalSizeCap>
        </rollingPolicy>
    </appender>

    <!-- Async Appender for Performance -->
    <appender name="ASYNC_JSON_FILE" class="ch.qos.logback.classic.AsyncAppender">
        <appender-ref ref="JSON_FILE"/>
        <queueSize>512</queueSize>
        <discardingThreshold>0</discardingThreshold>
        <includeCallerData>false</includeCallerData>
    </appender>

    <appender name="ASYNC_ERROR_FILE" class="ch.qos.logback.classic.AsyncAppender">
        <appender-ref ref="ERROR_FILE"/>
        <queueSize>256</queueSize>
        <discardingThreshold>0</discardingThreshold>
        <includeCallerData>true</includeCallerData>
    </appender>

    <!-- Security Audit File Appender -->
    <appender name="SECURITY_AUDIT" class="ch.qos.logback.core.rolling.RollingFileAppender">
        <file>${LOG_PATH:-${LOG_TEMP:-${java.io.tmpdir:-/tmp}}}/security-audit.log</file>
        <encoder class="net.logstash.logback.encoder.LogstashEncoder">
            <customFields>{"app_name":"${APP_NAME}","environment":"${ENVIRONMENT}","log_type":"security_audit"}</customFields>
            <includeContext>true</includeContext>
            <includeStructuredArguments>true</includeStructuredArguments>
            <timestampPattern>yyyy-MM-dd'T'HH:mm:ss.SSSZZ</timestampPattern>
        </encoder>
        <rollingPolicy class="ch.qos.logback.core.rolling.SizeAndTimeBasedRollingPolicy">
            <fileNamePattern>${LOG_PATH:-${LOG_TEMP:-${java.io.tmpdir:-/tmp}}}/security-audit.%d{yyyy-MM-dd}.%i.gz</fileNamePattern>
            <maxFileSize>100MB</maxFileSize>
            <maxHistory>365</maxHistory>
            <totalSizeCap>20GB</totalSizeCap>
        </rollingPolicy>
    </appender>

    <!-- Logger for Security Events -->
    <logger name="SECURITY_AUDIT" level="INFO" additivity="false">
        <appender-ref ref="SECURITY_AUDIT"/>
    </logger>

    <!-- Package-level Loggers -->
    <logger name="org.example" level="INFO"/>
    <logger name="org.example.security" level="DEBUG"/>
    <logger name="org.example.service" level="INFO"/>
    <logger name="org.example.controller" level="INFO"/>

    <!-- Spring Framework -->
    <logger name="org.springframework" level="INFO"/>
    <logger name="org.springframework.security" level="INFO"/>
    <logger name="org.springframework.web" level="INFO"/>

    <!-- Hibernate/JPA -->
    <logger name="org.hibernate.SQL" level="DEBUG"/>
    <logger name="org.hibernate.type.descriptor.sql.BasicBinder" level="TRACE"/>

    <!-- Flyway -->
    <logger name="org.flywaydb" level="INFO"/>

    <!-- Profile-specific configurations -->
    <springProfile name="dev">
        <root level="INFO">
            <appender-ref ref="CONSOLE"/>
            <appender-ref ref="JSON_FILE"/>
        </root>
    </springProfile>

    <springProfile name="test">
        <root level="WARN">
            <appender-ref ref="CONSOLE"/>
        </root>
    </springProfile>

    <springProfile name="prod">
        <root level="INFO">
            <appender-ref ref="JSON_CONSOLE"/>
            <appender-ref ref="ASYNC_JSON_FILE"/>
            <appender-ref ref="ASYNC_ERROR_FILE"/>
        </root>
    </springProfile>

    <!-- Default configuration -->
    <springProfile name="default">
        <root level="INFO">
            <appender-ref ref="CONSOLE"/>
            <appender-ref ref="JSON_FILE"/>
        </root>
    </springProfile>
</configuration>
